pyframe/__init__.py
pyframe/__main__.py
pyframe/app.py
pyframe/common.py
pyframe/controller.py
pyframe/indexer.py
pyframe/mqtt.py
pyframe/mylogging.py
pyframe/scheduler.py
pyframe/slideshow.py
pyframe/content/__init__.py
pyframe/content/base.py
pyframe/content/image.py
pyframe/content/video.py
repository/__init__.py
repository/common.py
repository/file.py
repository/index.py
repository/repository.py
repository/local/__init__.py
repository/local/file.py
repository/local/repository.py
repository/rclone/__init__.py
repository/rclone/file.py
repository/rclone/repository.py
repository/webdav/__init__.py
repository/webdav/file.py
repository/webdav/repository.py
01memories_resize-0.0.18.data/data/share/01memories/config/config-advanced.yaml
01memories_resize-0.0.18.data/data/share/01memories/config/config-simple.yaml
01memories_resize-0.0.18.data/data/share/01memories/config/config.yaml
01memories_resize-0.0.18.data/data/share/01memories/photos/examples/example1.jpg
01memories_resize-0.0.18.data/data/share/01memories/photos/examples/example2.jpg
01memories_resize-0.0.18.data/data/share/01memories/photos/examples/example3.jpg
01memories_resize-0.0.18.data/data/share/01memories/photos/examples/example4.jpg
01memories_resize-0.0.18.data/data/share/01memories/photos/examples/example5.jpg
01memories_resize-0.0.18.data/data/share/01memories/photos/examples/example6.jpg
01memories_resize-0.0.18.data/data/share/01memories/photos/examples/example7.jpg
01memories_resize-0.0.18.data/data/share/01memories/photos/examples/example8.jpg
01memories_resize-0.0.18.data/data/share/01memories/photos/examples/example9.jpg
01memories_resize-0.0.18.data/data/share/doc/01memories/Makefile
01memories_resize-0.0.18.data/data/share/doc/01memories/make.bat
01memories_resize-0.0.18.data/data/share/doc/01memories/source/conf.py
01memories_resize-0.0.18.data/data/share/doc/01memories/source/index.rst
01memories_resize-0.0.18.dist-info/METADATA
01memories_resize-0.0.18.dist-info/WHEEL
01memories_resize-0.0.18.dist-info/licenses/LICENSE.md
01memories_resize-0.0.18.dist-info/RECORD
