Metadata-Version: 2.1
Name: 01memories-resize
Version: 0.0.18
Summary: A digital photo frame application.
Project-URL: Homepage, https://github.com/kalbfuss/01memories
Project-URL: Issues, https://github.com/kalbfuss/01memories/issues
Author-email: Bernd Kalbfuss <kalbfuss@gmx.net>
License-File: LICENSE.md
Classifier: License :: OSI Approved :: GNU General Public License v3 (GPLv3)
Classifier: Operating System :: OS Independent
Classifier: Programming Language :: Python :: 3
Requires-Python: >=3.8
Requires-Dist: exifread
Requires-Dist: ffmpeg-python
Requires-Dist: geopy
Requires-Dist: iptcinfo3
Requires-Dist: kivy
Requires-Dist: paho-mqtt
Requires-Dist: pillow
Requires-Dist: pyyaml
Requires-Dist: rclone-python
Requires-Dist: schedule
Requires-Dist: sqlalchemy
Requires-Dist: webdavclient3
Requires-Dist: xdg-base-dirs
